improve_diarization_with_llm/__init__.py
improve_diarization_with_llm/_modidx.py
improve_diarization_with_llm/claude_corrector.py
improve_diarization_with_llm-0.0.4.dist-info/LICENSE
improve_diarization_with_llm-0.0.4.dist-info/METADATA
improve_diarization_with_llm-0.0.4.dist-info/WHEEL
improve_diarization_with_llm-0.0.4.dist-info/entry_points.txt
improve_diarization_with_llm-0.0.4.dist-info/top_level.txt
improve_diarization_with_llm-0.0.4.dist-info/RECORD
