Metadata-Version: 2.1
Name: improve-diarization-with-llm
Version: 0.0.4
Summary: This tool can take a long script (greater than 10 hours) of diarized content and improve the diarization by prompting an LLM model to look for obviously incorrect attribution and fix it.
Home-page: https://github.com/russedavid/improve-diarization-with-llm
Author: rijimuge
Author-email: david.russell04@gmail.com
License: Apache Software License 2.0
Keywords: nbdev jupyter notebook python
Classifier: Development Status :: 4 - Beta
Classifier: Intended Audience :: Developers
Classifier: Natural Language :: English
Classifier: Programming Language :: Python :: 3.7
Classifier: Programming Language :: Python :: 3.8
Classifier: Programming Language :: Python :: 3.9
Classifier: Programming Language :: Python :: 3.10
Classifier: License :: OSI Approved :: Apache Software License
Requires-Python: >=3.7
License-File: LICENSE
Requires-Dist: claudette
Provides-Extra: dev
